sparx/__init__.py
sparx/clustering.py
sparx/ffnn.py
sparx/main.py
sparx/merging.py
sparx/model_encoder.py
sparx/user_input.py
sparx/visualisation_graph.py
sparx/visualiser.py
sparx_lib-1.0.1.dist-info/LICENSE
sparx_lib-1.0.1.dist-info/METADATA
sparx_lib-1.0.1.dist-info/WHEEL
sparx_lib-1.0.1.dist-info/top_level.txt
sparx_lib-1.0.1.dist-info/RECORD
